slovene_form_generator/__init__.py
slovene_form_generator/form_generator.py
slovene_form_generator/mte6_translate.py
slovene_form_generator/models/logreg_adjectives.sav
slovene_form_generator/models/logreg_adverbs.sav
slovene_form_generator/models/logreg_feminine-nouns.sav
slovene_form_generator/models/logreg_masculine-nouns.sav
slovene_form_generator/models/logreg_neuter-nouns.sav
slovene_form_generator/models/logreg_verbs.sav
slovene_form_generator/resources/ending_parts_for_adjectives.tsv
slovene_form_generator/resources/ending_parts_for_adverbs.tsv
slovene_form_generator/resources/ending_parts_for_feminine_nouns.tsv
slovene_form_generator/resources/ending_parts_for_masculine_nouns.tsv
slovene_form_generator/resources/ending_parts_for_neuter_nouns.tsv
slovene_form_generator/resources/ending_parts_for_verbs.tsv
slovene_form_generator/resources/list_of_msds_for_lemmas.tsv
slovene_form_generator/resources/mte_6_dict_sl_en.tsv
slovene_form_generator/resources/pattern_remapping.tsv
slovene_form_generator/resources/patterns_for_generation.tsv
slovene_form_generator-0.0.17.dist-info/LICENSE
slovene_form_generator-0.0.17.dist-info/METADATA
slovene_form_generator-0.0.17.dist-info/WHEEL
slovene_form_generator-0.0.17.dist-info/top_level.txt
slovene_form_generator-0.0.17.dist-info/RECORD
