Metadata-Version: 2.1
Name: slovene-form-generator
Version: 0.0.17
Summary: slovene word inflector / form generator
Home-page: UNKNOWN
Author: Peter Pisljar
License: UNKNOWN
Platform: UNKNOWN
Requires-Python: >=3.8.0, <3.12
License-File: LICENSE
Requires-Dist: scikit-learn (==1.0.2)
